phix/__init__.py
phix-0.6.1.dist-info/DESCRIPTION.rst
phix-0.6.1.dist-info/METADATA
phix-0.6.1.dist-info/RECORD
phix-0.6.1.dist-info/WHEEL
phix-0.6.1.dist-info/entry_points.txt
phix-0.6.1.dist-info/metadata.json
phix-0.6.1.dist-info/top_level.txt
