Metadata-Version: 2.0
Name: phix
Version: 0.6.1
Summary: Make writing your Sphinx docs a little easier.
Home-page: https://github.com/wlonk/phix
Author: Kit La Touche
Author-email: kit@transneptune.net
License: MIT
Download-URL: https://github.com/wlonk/phix/tarball/0.6.1
Keywords: Sphinx
Platform: UNKNOWN
Classifier: Development Status :: 3 - Alpha
Classifier: Intended Audience :: Developers
Classifier: Programming Language :: Python :: 3
Classifier: Programming Language :: Python :: 3.3
Classifier: Programming Language :: Python :: 3.4
Classifier: Programming Language :: Python :: 3.5
Classifier: Programming Language :: Python :: 3.6
Classifier: License :: OSI Approved :: MIT License
Requires-Python: >=3.0
Requires-Dist: watchdog
Requires-Dist: click
